epe_maria/__init__.py
epe_maria/benchmark.py
epe_maria/core.py
epe_maria/metrics.py
epe_maria/monitor.py
epe_maria/temporal.py
epe_maria/test_temporal.py
lady_epe-0.1.0.dist-info/METADATA
lady_epe-0.1.0.dist-info/WHEEL
lady_epe-0.1.0.dist-info/top_level.txt
lady_epe-0.1.0.dist-info/RECORD
