Metadata-Version: 2.4
Name: lady-epe
Version: 0.1.0
Summary: Framework simbólico para auditoria de modelos com métricas de divergência temporal
Author: Cesar Rúbio
Author-email: teu@email.com
License: MIT
Classifier: Programming Language :: Python :: 3
Classifier: Operating System :: OS Independent
Requires-Python: >=3.8
Requires-Dist: numpy
Requires-Dist: scipy
Requires-Dist: matplotlib
Dynamic: author
Dynamic: author-email
Dynamic: classifier
Dynamic: requires-dist
Dynamic: summary
